loop_step/__init__.py
loop_step/_version.py
loop_step/loop.py
loop_step/loop_parameters.py
loop_step/loop_step.py
loop_step/tk_loop.py
loop_step-2025.7.23.dist-info/licenses/AUTHORS.rst
loop_step-2025.7.23.dist-info/licenses/LICENSE
loop_step-2025.7.23.dist-info/METADATA
loop_step-2025.7.23.dist-info/WHEEL
loop_step-2025.7.23.dist-info/entry_points.txt
loop_step-2025.7.23.dist-info/top_level.txt
loop_step-2025.7.23.dist-info/RECORD
